hyper_requests/__init__.py
hyper_requests/request_builder.py
hyper_requests/threader.py
hyper_requests-0.0.12.dist-info/METADATA
hyper_requests-0.0.12.dist-info/WHEEL
hyper_requests-0.0.12.dist-info/licenses/LICENSE
hyper_requests-0.0.12.dist-info/RECORD
