Metadata-Version: 2.4
Name: hyper-requests
Version: 0.0.12
Summary: Concurrent request HTTP execution library
Project-URL: Homepage, https://github.com/edjones84/hyper-requests
Project-URL: Bug Tracker, https://github.com/edjones84/hyper-requests/issues
Author-email: Ed Jones <ejones84@icloud.com>
License-File: LICENSE
Classifier: License :: OSI Approved :: MIT License
Classifier: Operating System :: OS Independent
Classifier: Programming Language :: Python :: 3
Requires-Python: >=3.7
Requires-Dist: nest-asyncio~=1.6.0
Requires-Dist: requests~=2.32.2
